{
  "customers": [
    {"customer_id": "cust_abc_001", "name": "Alex", "email": "alex@company.com", "phone": "+1234567890", "city": "New York", "total_orders": 15, "loyalty_points": 250},
    {"customer_id": "cust_def_002", "name": "Sofia", "email": "sofia@company.com", "phone": "+1987654321", "city": "London", "total_orders": 8, "loyalty_points": 120},
    {"customer_id": "cust_xyz_003", "name": "Max", "email": "max@company.com", "phone": "+1122334455", "city": "Berlin", "total_orders": 22, "loyalty_points": 380},
    {"customer_id": "cust_123_004", "name": "Olga", "email": "olga@company.com", "phone": "+1555666777", "city": "Paris", "total_orders": 12, "loyalty_points": 180},
    {"customer_id": "cust_mno_005", "name": "Victor", "email": "victor@company.com", "phone": "+1444333222", "city": "Tokyo", "total_orders": 30, "loyalty_points": 500}
  ]
}